looming_spots/__init__.py
looming_spots/box_corner_coordinates.npy
looming_spots/constants.py
looming_spots/exceptions.py
looming_spots/process_experiment.py
looming_spots/track_mouse.sh
looming_spots/analyse/__init__.py
looming_spots/analyse/arena_region_crossings.py
looming_spots/analyse/escape_classification.py
looming_spots/analyse/tracks.py
looming_spots/db/__init__.py
looming_spots/db/loom_trial_group.py
looming_spots/db/session.py
looming_spots/db/track.py
looming_spots/db/trial.py
looming_spots/loom_io/__init__.py
looming_spots/loom_io/photodiode.py
looming_spots/loom_io/session_io.py
looming_spots/util/__init__.py
looming_spots/util/box_coordinates_selector_tool.py
looming_spots/util/generate_example_videos.py
looming_spots/util/generic_functions.py
looming_spots/util/plotting.py
looming_spots/util/transformations.py
looming_spots/util/video_processing.py
looming_spots/util/manual_tracking/__init__.py
looming_spots/util/manual_tracking/viewer_tracker.py
looming_spots-0.1.0.dist-info/METADATA
looming_spots-0.1.0.dist-info/WHEEL
looming_spots-0.1.0.dist-info/top_level.txt
looming_spots-0.1.0.dist-info/RECORD
