Metadata-Version: 2.1
Name: looming_spots
Version: 0.1.0
Summary: looming experiment analysis
Author-email: Stephen Lenzi <stephen.lenzi@gmail.com>
License: MIT
Project-URL: Homepage, https://github.com/stephenlenzi/looming_spots
Project-URL: Bug Tracker, https://github.com/stephenlenzi/looming_spots/issues
Project-URL: Documentation, https://stephenlenzi.github.io/looming_spots
Project-URL: Source Code, https://github.com/stephenlenzi/looming_spots
Project-URL: User Support, https://github.com/stephenlenzi/looming_spots/issues
Classifier: Development Status :: 2 - Pre-Alpha
Classifier: Programming Language :: Python
Classifier: Programming Language :: Python :: 3
Classifier: Programming Language :: Python :: 3.9
Classifier: Programming Language :: Python :: 3.10
Classifier: Programming Language :: Python :: 3.11
Classifier: Operating System :: OS Independent
Classifier: License :: OSI Approved :: MIT License
Requires-Python: >=3.9.0
Requires-Dist: numpy
Requires-Dist: configobj
Requires-Dist: matplotlib
Requires-Dist: seaborn
Requires-Dist: scipy
Requires-Dist: pandas
Requires-Dist: pims
Requires-Dist: scikit-video
Requires-Dist: pingouin
Requires-Dist: nptdms
Requires-Dist: cached-property
Requires-Dist: tqdm
Requires-Dist: scikit-image
Requires-Dist: opencv-python
Requires-Dist: tables
Requires-Dist: more-itertools
Requires-Dist: fire
Requires-Dist: daq-loader
Provides-Extra: dev
Requires-Dist: pytest; extra == "dev"
Requires-Dist: pytest-cov; extra == "dev"
Requires-Dist: coverage; extra == "dev"
Requires-Dist: tox; extra == "dev"
Requires-Dist: mypy; extra == "dev"
Requires-Dist: pre-commit; extra == "dev"
Requires-Dist: ruff; extra == "dev"
Requires-Dist: setuptools-scm; extra == "dev"
